{
    "page": 4,
    "itemsPerPage": 25,
    "items": [
        {
            "registerReadingId": 413753,
            "registerId": 1935,
            "accountId": 1831,
            "meterId": 1839,
            "meterPointId": 2102,
            "meterReadingId": 156584,
            "meterPointType": "E",
            "meterPointNumber": 2000007794886,
            "meterSerialNumber": "D00C33911",
            "registerReference": "01",
            "meterReadingDateTime": "2018-04-16T00:00:00",
            "readingValue": 10508.0,
            "meterReadingTypeUID": "ESTIMATED",
            "meterReadingSourceUID": "ESTIMATE",
            "meterReadingStatusUID": "INVALID",
            "billable": false,
            "required": true,
            "meterReadingCreatedDate": "2018-06-12T15:38:26.613",
            "hasLiveCharge": false,
            "hasRegisterAdvance": true
        },
        {
            "registerReadingId": 422566,
            "registerId": 1935,
            "accountId": 1831,
            "meterId": 1839,
            "meterPointId": 2102,
            "meterReadingId": 164923,
            "meterPointType": "E",
            "meterPointNumber": 2000007794886,
            "meterSerialNumber": "D00C33911",
            "registerReference": "01",
            "meterReadingDateTime": "2018-04-16T00:00:00",
            "readingValue": 10508.0,
            "meterReadingTypeUID": "ESTIMATED",
            "meterReadingSourceUID": "ESTIMATE",
            "meterReadingStatusUID": "VALID",
            "billable": true,
            "required": true,
            "meterReadingCreatedDate": "2018-06-26T15:33:37.467",
            "hasLiveCharge": true,
            "hasRegisterAdvance": true
        },
        {
            "registerReadingId": 324268,
            "registerId": 1935,
            "accountId": 1831,
            "meterId": 1839,
            "meterPointId": 2102,
            "meterReadingId": 68462,
            "meterPointType": "E",
            "meterPointNumber": 2000007794886,
            "meterSerialNumber": "D00C33911",
            "registerReference": "01",
            "meterReadingDateTime": "2018-03-17T00:00:00",
            "readingValue": 10958.7,
            "meterReadingTypeUID": "ESTIMATED",
            "meterReadingSourceUID": "ESTIMATE",
            "meterReadingStatusUID": "INVALID",
            "billable": false,
            "required": false,
            "meterReadingCreatedDate": "2018-03-17T00:12:34.637",
            "hasLiveCharge": false,
            "hasRegisterAdvance": true
        },
        {
            "registerReadingId": 312567,
            "registerId": 1935,
            "accountId": 1831,
            "meterId": 1839,
            "meterPointId": 2102,
            "meterReadingId": 57052,
            "meterPointType": "E",
            "meterPointNumber": 2000007794886,
            "meterSerialNumber": "D00C33911",
            "registerReference": "01",
            "meterReadingDateTime": "2018-02-16T00:00:00",
            "readingValue": 10347.0,
            "meterReadingTypeUID": "ACTUAL",
            "meterReadingSourceUID": "CUSTOMER",
            "meterReadingStatusUID": "VALID",
            "billable": true,
            "required": false,
            "meterReadingCreatedDate": "2018-02-16T16:32:18.753",
            "hasLiveCharge": true,
            "hasRegisterAdvance": true
        },
        {
            "registerReadingId": 301404,
            "registerId": 1935,
            "accountId": 1831,
            "meterId": 1839,
            "meterPointId": 2102,
            "meterReadingId": 46106,
            "meterPointType": "E",
            "meterPointNumber": 2000007794886,
            "meterSerialNumber": "D00C33911",
            "registerReference": "01",
            "meterReadingDateTime": "2018-01-16T00:00:00",
            "readingValue": 9547.0,
            "meterReadingTypeUID": "ACTUAL",
            "meterReadingSourceUID": "CUSTOMER",
            "meterReadingStatusUID": "VALID",
            "billable": true,
            "required": false,
            "meterReadingCreatedDate": "2018-01-16T16:53:47.24",
            "hasLiveCharge": true,
            "hasRegisterAdvance": true
        },
        {
            "registerReadingId": 39089,
            "registerId": 1935,
            "accountId": 1831,
            "meterId": 1839,
            "meterPointId": 2102,
            "meterReadingId": 39053,
            "meterPointType": "E",
            "meterPointNumber": 2000007794886,
            "meterSerialNumber": "D00C33911",
            "registerReference": "01",
            "meterReadingDateTime": "2017-12-25T00:00:00",
            "readingValue": 8767.0,
            "meterReadingTypeUID": "ACTUAL",
            "meterReadingSourceUID": "CUSTOMER",
            "meterReadingStatusUID": "INVALID",
            "billable": false,
            "required": false,
            "meterReadingCreatedDate": "2017-12-25T18:54:13.99",
            "hasLiveCharge": false,
            "hasRegisterAdvance": true
        },
        {
            "registerReadingId": 39090,
            "registerId": 1935,
            "accountId": 1831,
            "meterId": 1839,
            "meterPointId": 2102,
            "meterReadingId": 39054,
            "meterPointType": "E",
            "meterPointNumber": 2000007794886,
            "meterSerialNumber": "D00C33911",
            "registerReference": "01",
            "meterReadingDateTime": "2017-12-25T00:00:00",
            "readingValue": 8767.0,
            "meterReadingTypeUID": "ACTUAL",
            "meterReadingSourceUID": "CUSTOMER",
            "meterReadingStatusUID": "INVALID",
            "billable": false,
            "required": false,
            "meterReadingCreatedDate": "2017-12-25T18:54:35.697",
            "hasLiveCharge": false,
            "hasRegisterAdvance": true
        },
        {
            "registerReadingId": 36104,
            "registerId": 1935,
            "accountId": 1831,
            "meterId": 1839,
            "meterPointId": 2102,
            "meterReadingId": 35994,
            "meterPointType": "E",
            "meterPointNumber": 2000007794886,
            "meterSerialNumber": "D00C33911",
            "registerReference": "01",
            "meterReadingDateTime": "2017-12-12T00:00:00",
            "readingValue": 8767.0,
            "meterReadingTypeUID": "ACTUAL",
            "meterReadingSourceUID": "CUSTOMER",
            "meterReadingStatusUID": "VALID",
            "billable": true,
            "required": false,
            "meterReadingCreatedDate": "2017-12-12T17:01:23.303",
            "hasLiveCharge": true,
            "hasRegisterAdvance": true
        },
        {
            "registerReadingId": 29734,
            "registerId": 1935,
            "accountId": 1831,
            "meterId": 1839,
            "meterPointId": 2102,
            "meterReadingId": 29456,
            "meterPointType": "E",
            "meterPointNumber": 2000007794886,
            "meterSerialNumber": "D00C33911",
            "registerReference": "01",
            "meterReadingDateTime": "2017-11-12T00:00:00",
            "readingValue": 8005.0,
            "meterReadingTypeUID": "ACTUAL",
            "meterReadingSourceUID": "CUSTOMER",
            "meterReadingStatusUID": "VALID",
            "billable": true,
            "required": false,
            "meterReadingCreatedDate": "2017-11-12T18:39:22.547",
            "hasLiveCharge": true,
            "hasRegisterAdvance": true
        },
        {
            "registerReadingId": 26297,
            "registerId": 1935,
            "accountId": 1831,
            "meterId": 1839,
            "meterPointId": 2102,
            "meterReadingId": 26098,
            "meterPointType": "E",
            "meterPointNumber": 2000007794886,
            "meterSerialNumber": "D00C33911",
            "registerReference": "01",
            "meterReadingDateTime": "2017-10-12T00:00:00",
            "readingValue": 7243.0,
            "meterReadingTypeUID": "ACTUAL",
            "meterReadingSourceUID": "CUSTOMER",
            "meterReadingStatusUID": "VALID",
            "billable": true,
            "required": false,
            "meterReadingCreatedDate": "2017-10-12T16:09:39.573",
            "hasLiveCharge": true,
            "hasRegisterAdvance": true
        },
        {
            "registerReadingId": 14549,
            "registerId": 1935,
            "accountId": 1831,
            "meterId": 1839,
            "meterPointId": 2102,
            "meterReadingId": 14395,
            "meterPointType": "E",
            "meterPointNumber": 2000007794886,
            "meterSerialNumber": "D00C33911",
            "registerReference": "01",
            "meterReadingDateTime": "2017-09-20T00:00:00",
            "readingValue": 6708.0,
            "meterReadingTypeUID": "ACTUAL",
            "meterReadingSourceUID": "CUSTOMER",
            "meterReadingStatusUID": "INVALID",
            "billable": false,
            "required": false,
            "meterReadingCreatedDate": "2017-09-20T08:16:02.13",
            "hasLiveCharge": false,
            "hasRegisterAdvance": true
        },
        {
            "registerReadingId": 13699,
            "registerId": 1935,
            "accountId": 1831,
            "meterId": 1839,
            "meterPointId": 2102,
            "meterReadingId": 13595,
            "meterPointType": "E",
            "meterPointNumber": 2000007794886,
            "meterSerialNumber": "D00C33911",
            "registerReference": "01",
            "meterReadingDateTime": "2017-09-06T00:00:00",
            "readingValue": 6446.0,
            "meterReadingTypeUID": "ACTUAL",
            "meterReadingSourceUID": "CUSTOMER",
            "meterReadingStatusUID": "INVALID",
            "billable": false,
            "required": false,
            "meterReadingCreatedDate": "2017-09-06T11:27:16.643",
            "hasLiveCharge": false,
            "hasRegisterAdvance": true
        },
        {
            "registerReadingId": 13184,
            "registerId": 1935,
            "accountId": 1831,
            "meterId": 1839,
            "meterPointId": 2102,
            "meterReadingId": 13091,
            "meterPointType": "E",
            "meterPointNumber": 2000007794886,
            "meterSerialNumber": "D00C33911",
            "registerReference": "01",
            "meterReadingDateTime": "2017-08-24T00:00:00",
            "readingValue": 6234.0,
            "meterReadingTypeUID": "ACTUAL",
            "meterReadingSourceUID": "CUSTOMER",
            "meterReadingStatusUID": "INVALID",
            "billable": false,
            "required": false,
            "meterReadingCreatedDate": "2017-08-24T07:38:08.143",
            "hasLiveCharge": false,
            "hasRegisterAdvance": true
        },
        {
            "registerReadingId": 13060,
            "registerId": 1935,
            "accountId": 1831,
            "meterId": 1839,
            "meterPointId": 2102,
            "meterReadingId": 12972,
            "meterPointType": "E",
            "meterPointNumber": 2000007794886,
            "meterSerialNumber": "D00C33911",
            "registerReference": "01",
            "meterReadingDateTime": "2017-08-18T00:00:00",
            "readingValue": 6136.0,
            "meterReadingTypeUID": "ACTUAL",
            "meterReadingSourceUID": "CUSTOMER",
            "meterReadingStatusUID": "INVALID",
            "billable": false,
            "required": false,
            "meterReadingCreatedDate": "2017-08-18T08:23:37.603",
            "hasLiveCharge": false,
            "hasRegisterAdvance": true
        },
        {
            "registerReadingId": 12955,
            "registerId": 1935,
            "accountId": 1831,
            "meterId": 1839,
            "meterPointId": 2102,
            "meterReadingId": 12872,
            "meterPointType": "E",
            "meterPointNumber": 2000007794886,
            "meterSerialNumber": "D00C33911",
            "registerReference": "01",
            "meterReadingDateTime": "2017-07-24T00:00:00",
            "readingValue": 6019.9,
            "meterReadingTypeUID": "ESTIMATED",
            "meterReadingSourceUID": "ESTIMATE",
            "meterReadingStatusUID": "INVALID",
            "billable": false,
            "required": true,
            "meterReadingCreatedDate": "2017-08-04T12:41:20.397",
            "hasLiveCharge": false,
            "hasRegisterAdvance": true
        },
        {
            "registerReadingId": 13061,
            "registerId": 1935,
            "accountId": 1831,
            "meterId": 1839,
            "meterPointId": 2102,
            "meterReadingId": 12973,
            "meterPointType": "E",
            "meterPointNumber": 2000007794886,
            "meterSerialNumber": "D00C33911",
            "registerReference": "01",
            "meterReadingDateTime": "2017-07-24T00:00:00",
            "readingValue": 6019.9,
            "meterReadingTypeUID": "ESTIMATED",
            "meterReadingSourceUID": "ESTIMATE",
            "meterReadingStatusUID": "INVALID",
            "billable": false,
            "required": true,
            "meterReadingCreatedDate": "2017-08-18T08:23:21.877",
            "hasLiveCharge": false,
            "hasRegisterAdvance": true
        },
        {
            "registerReadingId": 371181,
            "registerId": 1935,
            "accountId": 1831,
            "meterId": 1839,
            "meterPointId": 2102,
            "meterReadingId": 114619,
            "meterPointType": "E",
            "meterPointNumber": 2000007794886,
            "meterSerialNumber": "D00C33911",
            "registerReference": "01",
            "meterReadingDateTime": "2017-07-24T00:00:00",
            "readingValue": 5747.2,
            "meterReadingTypeUID": "ESTIMATED",
            "meterReadingSourceUID": "ESTIMATE",
            "meterReadingStatusUID": "INVALID",
            "billable": false,
            "required": true,
            "meterReadingCreatedDate": "2018-05-23T08:56:10.373",
            "hasLiveCharge": false,
            "hasRegisterAdvance": true
        },
        {
            "registerReadingId": 422559,
            "registerId": 1935,
            "accountId": 1831,
            "meterId": 1839,
            "meterPointId": 2102,
            "meterReadingId": 164917,
            "meterPointType": "E",
            "meterPointNumber": 2000007794886,
            "meterSerialNumber": "D00C33911",
            "registerReference": "01",
            "meterReadingDateTime": "2017-07-24T00:00:00",
            "readingValue": 5747.2,
            "meterReadingTypeUID": "ESTIMATED",
            "meterReadingSourceUID": "ESTIMATE",
            "meterReadingStatusUID": "INVALID",
            "billable": false,
            "required": true,
            "meterReadingCreatedDate": "2018-06-26T15:29:45.68",
            "hasLiveCharge": false,
            "hasRegisterAdvance": true
        },
        {
            "registerReadingId": 422560,
            "registerId": 1935,
            "accountId": 1831,
            "meterId": 1839,
            "meterPointId": 2102,
            "meterReadingId": 164918,
            "meterPointType": "E",
            "meterPointNumber": 2000007794886,
            "meterSerialNumber": "D00C33911",
            "registerReference": "01",
            "meterReadingDateTime": "2017-07-24T00:00:00",
            "readingValue": 5750.8,
            "meterReadingTypeUID": "ESTIMATED",
            "meterReadingSourceUID": "ESTIMATE",
            "meterReadingStatusUID": "INVALID",
            "billable": false,
            "required": true,
            "meterReadingCreatedDate": "2018-06-26T15:30:17.39",
            "hasLiveCharge": false,
            "hasRegisterAdvance": true
        },
        {
            "registerReadingId": 422564,
            "registerId": 1935,
            "accountId": 1831,
            "meterId": 1839,
            "meterPointId": 2102,
            "meterReadingId": 164921,
            "meterPointType": "E",
            "meterPointNumber": 2000007794886,
            "meterSerialNumber": "D00C33911",
            "registerReference": "01",
            "meterReadingDateTime": "2017-07-24T00:00:00",
            "readingValue": 5757.3,
            "meterReadingTypeUID": "ESTIMATED",
            "meterReadingSourceUID": "ESTIMATE",
            "meterReadingStatusUID": "INVALID",
            "billable": false,
            "required": true,
            "meterReadingCreatedDate": "2018-06-26T15:31:40.757",
            "hasLiveCharge": false,
            "hasRegisterAdvance": true
        },
        {
            "registerReadingId": 422565,
            "registerId": 1935,
            "accountId": 1831,
            "meterId": 1839,
            "meterPointId": 2102,
            "meterReadingId": 164922,
            "meterPointType": "E",
            "meterPointNumber": 2000007794886,
            "meterSerialNumber": "D00C33911",
            "registerReference": "01",
            "meterReadingDateTime": "2017-07-24T00:00:00",
            "readingValue": 5885.8,
            "meterReadingTypeUID": "ESTIMATED",
            "meterReadingSourceUID": "ESTIMATE",
            "meterReadingStatusUID": "VALID",
            "billable": true,
            "required": true,
            "meterReadingCreatedDate": "2018-06-26T15:32:13.96",
            "hasLiveCharge": true,
            "hasRegisterAdvance": true
        },
        {
            "registerReadingId": 12889,
            "registerId": 1935,
            "accountId": 1831,
            "meterId": 1839,
            "meterPointId": 2102,
            "meterReadingId": 12809,
            "meterPointType": "E",
            "meterPointNumber": 2000007794886,
            "meterSerialNumber": "D00C33911",
            "registerReference": "01",
            "meterReadingDateTime": "2017-07-13T00:00:00",
            "readingValue": 5755.0,
            "meterReadingTypeUID": "ACTUAL",
            "meterReadingSourceUID": "CUSTOMER",
            "meterReadingStatusUID": "INVALID",
            "billable": false,
            "required": false,
            "meterReadingCreatedDate": "2017-07-13T12:12:04.08",
            "hasLiveCharge": false,
            "hasRegisterAdvance": true
        },
        {
            "registerReadingId": 12846,
            "registerId": 1935,
            "accountId": 1831,
            "meterId": 1839,
            "meterPointId": 2102,
            "meterReadingId": 12768,
            "meterPointType": "E",
            "meterPointNumber": 2000007794886,
            "meterSerialNumber": "D00C33911",
            "registerReference": "01",
            "meterReadingDateTime": "2017-06-19T00:00:00",
            "readingValue": 5327.0,
            "meterReadingTypeUID": "ACTUAL",
            "meterReadingSourceUID": "CUSTOMER",
            "meterReadingStatusUID": "INVALID",
            "billable": false,
            "required": false,
            "meterReadingCreatedDate": "2017-06-19T09:45:07.187",
            "hasLiveCharge": false,
            "hasRegisterAdvance": false
        },
        {
            "registerReadingId": 12867,
            "registerId": 1935,
            "accountId": 1831,
            "meterId": 1839,
            "meterPointId": 2102,
            "meterReadingId": 12788,
            "meterPointType": "E",
            "meterPointNumber": 2000007794886,
            "meterSerialNumber": "D00C33911",
            "registerReference": "01",
            "meterReadingDateTime": "2017-04-17T00:00:00",
            "readingValue": 4223.3,
            "meterReadingTypeUID": "ACTUAL",
            "meterReadingSourceUID": "DC",
            "meterReadingStatusUID": "VALID",
            "billable": true,
            "required": false,
            "meterReadingCreatedDate": "2017-06-27T00:25:34",
            "hasLiveCharge": false,
            "hasRegisterAdvance": false
        },
        {
            "registerReadingId": 12815,
            "registerId": 1935,
            "accountId": 1831,
            "meterId": 1839,
            "meterPointId": 2102,
            "meterReadingId": 12738,
            "meterPointType": "E",
            "meterPointNumber": 2000007794886,
            "meterSerialNumber": "D00C33911",
            "registerReference": "01",
            "meterReadingDateTime": "2017-04-12T10:05:56.65",
            "readingValue": 4119.0,
            "meterReadingTypeUID": "ACTUAL",
            "meterReadingSourceUID": "CUSTOMER",
            "meterReadingStatusUID": "INVALID",
            "billable": false,
            "required": false,
            "meterReadingCreatedDate": "2017-04-18T10:06:16.613",
            "hasLiveCharge": false,
            "hasRegisterAdvance": false
        }
    ],
    "total": 100,
    "totalPages": 4
}